infradrone/__init__.py
infradrone/__main__.py
infradrone/config.py
infradrone/deploy.py
infradrone/infra_operations.py
infradrone/utils.py
infradrone/menus/__init__.py
infradrone/menus/deploy_docker.py
infradrone/menus/deploy_infra_instance.py
infradrone/menus/help_menu.py
infradrone/menus/main_menu.py
infradrone/menus/ssh_connections.py
infradrone-0.1.1.dist-info/licenses/LICENSE
infradrone-0.1.1.dist-info/METADATA
infradrone-0.1.1.dist-info/WHEEL
infradrone-0.1.1.dist-info/top_level.txt
infradrone-0.1.1.dist-info/RECORD
