Metadata-Version: 2.4
Name: infradrone
Version: 0.1.1
Summary: Infrastructure deployment automation toolkit
Author-email: Anton Pavlenko <apavlenko@hmcorp.uk>
License-Expression: MIT
Project-URL: Homepage, https://github.com/HMCorp-Fund/infradrone
Project-URL: Tracker, https://github.com/HMCorp-Fund/infradrone/issues
Requires-Python: >=3.8
License-File: LICENSE
Requires-Dist: paramiko>=3.5.1
Requires-Dist: curses-menu>=0.9.0
Dynamic: license-file
